<?xml version="1.0" encoding="UTF-8" ?>
<!DOCTYPE mapper PUBLIC "-//mybatis.org//DTD Mapper 3.0//EN" "http://mybatis.org/dtd/mybatis-3-mapper.dtd" >
<mapper namespace="cn.enjoy.mall.dao.SysParamMapper" >
  <resultMap id="BaseResultMap" type="cn.enjoy.sys.model.SysParam" >
    <!--
      WARNING - @mbggenerated
      This element is automatically generated by MyBatis Generator, do not modify.
      This element was generated on Tue Oct 31 09:13:55 CST 2017.
    -->
    <id column="id" property="id" jdbcType="INTEGER" />
    <result column="code" property="code" jdbcType="VARCHAR" />
    <result column="value" property="value" jdbcType="VARCHAR" />
    <result column="is_valid" property="isValid" jdbcType="INTEGER" />
    <result column="description" property="description" jdbcType="VARCHAR" />
    <result column="update_time" property="updateTime" jdbcType="TIMESTAMP" />
  </resultMap>
  <sql id="Base_Column_List" >
    <!--
      WARNING - @mbggenerated
      This element is automatically generated by MyBatis Generator, do not modify.
      This element was generated on Tue Oct 31 09:13:55 CST 2017.
    -->
    id, code, value, is_valid, description, update_time
  </sql>
  <select id="selectByPrimaryKey" resultMap="BaseResultMap" parameterType="java.lang.Integer" >
    <!--
      WARNING - @mbggenerated
      This element is automatically generated by MyBatis Generator, do not modify.
      This element was generated on Tue Oct 31 09:13:55 CST 2017.
    -->
    select 
    <include refid="Base_Column_List" />
    from sys_param
    where id = #{id,jdbcType=INTEGER}
  </select>
  <delete id="deleteByPrimaryKey" parameterType="java.lang.Integer" >
    <!--
      WARNING - @mbggenerated
      This element is automatically generated by MyBatis Generator, do not modify.
      This element was generated on Tue Oct 31 09:13:55 CST 2017.
    -->
    delete from sys_param
    where id = #{id,jdbcType=INTEGER}
  </delete>
  <insert id="insert" parameterType="cn.enjoy.sys.model.SysParam" >
    <!--
      WARNING - @mbggenerated
      This element is automatically generated by MyBatis Generator, do not modify.
      This element was generated on Tue Oct 31 09:13:55 CST 2017.
    -->
    insert into sys_param (id, code, value, 
      is_valid, description, update_time
      )
    values (#{id,jdbcType=INTEGER}, #{code,jdbcType=VARCHAR}, #{value,jdbcType=VARCHAR}, 
      #{isValid,jdbcType=INTEGER}, #{description,jdbcType=VARCHAR}, #{updateTime,jdbcType=TIMESTAMP}
      )
  </insert>
  <insert id="insertSelective" parameterType="cn.enjoy.sys.model.SysParam" >
    <!--
      WARNING - @mbggenerated
      This element is automatically generated by MyBatis Generator, do not modify.
      This element was generated on Tue Oct 31 09:13:55 CST 2017.
    -->
    insert into sys_param
    <trim prefix="(" suffix=")" suffixOverrides="," >
      <if test="id != null" >
        id,
      </if>
      <if test="code != null" >
        code,
      </if>
      <if test="value != null" >
        value,
      </if>
      <if test="isValid != null" >
        is_valid,
      </if>
      <if test="description != null" >
        description,
      </if>
      <if test="updateTime != null" >
        update_time,
      </if>
    </trim>
    <trim prefix="values (" suffix=")" suffixOverrides="," >
      <if test="id != null" >
        #{id,jdbcType=INTEGER},
      </if>
      <if test="code != null" >
        #{code,jdbcType=VARCHAR},
      </if>
      <if test="value != null" >
        #{value,jdbcType=VARCHAR},
      </if>
      <if test="isValid != null" >
        #{isValid,jdbcType=INTEGER},
      </if>
      <if test="description != null" >
        #{description,jdbcType=VARCHAR},
      </if>
      <if test="updateTime != null" >
        #{updateTime,jdbcType=TIMESTAMP},
      </if>
    </trim>
  </insert>
  <update id="updateByPrimaryKeySelective" parameterType="cn.enjoy.sys.model.SysParam" >
    <!--
      WARNING - @mbggenerated
      This element is automatically generated by MyBatis Generator, do not modify.
      This element was generated on Tue Oct 31 09:13:55 CST 2017.
    -->
    update sys_param
    <set >
      <if test="code != null" >
        code = #{code,jdbcType=VARCHAR},
      </if>
      <if test="value != null" >
        value = #{value,jdbcType=VARCHAR},
      </if>
      <if test="isValid != null" >
        is_valid = #{isValid,jdbcType=INTEGER},
      </if>
      <if test="description != null" >
        description = #{description,jdbcType=VARCHAR},
      </if>
      <if test="updateTime != null" >
        update_time = #{updateTime,jdbcType=TIMESTAMP},
      </if>
    </set>
    where id = #{id,jdbcType=INTEGER}
  </update>
  <update id="updateByPrimaryKey" parameterType="cn.enjoy.sys.model.SysParam" >
    <!--
      WARNING - @mbggenerated
      This element is automatically generated by MyBatis Generator, do not modify.
      This element was generated on Tue Oct 31 09:13:55 CST 2017.
    -->
    update sys_param
    set code = #{code,jdbcType=VARCHAR},
      value = #{value,jdbcType=VARCHAR},
      is_valid = #{isValid,jdbcType=INTEGER},
      description = #{description,jdbcType=VARCHAR},
      update_time = #{updateTime,jdbcType=TIMESTAMP}
    where id = #{id,jdbcType=INTEGER}
  </update>

  <select id="selectByCode" resultMap="BaseResultMap" parameterType="java.lang.String" >

  select
  <include refid="Base_Column_List" />
  from sys_param
  where is_valid = 1 and code  = #{code}
  </select>
</mapper>